_version.py
scp_uploader.py
PyUpdater_SCP_Plugin-4.0.3.dist-info/METADATA
PyUpdater_SCP_Plugin-4.0.3.dist-info/WHEEL
PyUpdater_SCP_Plugin-4.0.3.dist-info/entry_points.txt
PyUpdater_SCP_Plugin-4.0.3.dist-info/pbr.json
PyUpdater_SCP_Plugin-4.0.3.dist-info/top_level.txt
PyUpdater_SCP_Plugin-4.0.3.dist-info/RECORD
